legacy_import_migrator/__init__.py
legacy_import_migrator/__main__.py
legacy_import_migrator/checker.py
legacy_import_migrator/tracker.py
legacy_import_migrator/cli/__init__.py
legacy_import_migrator/cli/baseline.py
legacy_import_migrator/cli/check.py
legacy_import_migrator/cli/scan.py
legacy_import_migrator-0.1.1.dist-info/METADATA
legacy_import_migrator-0.1.1.dist-info/WHEEL
legacy_import_migrator-0.1.1.dist-info/entry_points.txt
legacy_import_migrator-0.1.1.dist-info/licenses/LICENSE
legacy_import_migrator-0.1.1.dist-info/RECORD
