Metadata-Version: 2.4
Name: legacy-import-migrator
Version: 0.1.1
Summary: AST-based legacy import tracking and migration toolkit for Python codebases
Project-URL: Homepage, https://github.com/strataregula/legacy-import-migrator
Project-URL: Repository, https://github.com/strataregula/legacy-import-migrator
Project-URL: Issues, https://github.com/strataregula/legacy-import-migrator/issues
Author-email: Legacy Import Migrator Team <team@strataregula.com>
License: Apache-2.0
License-File: LICENSE
Classifier: Development Status :: 4 - Beta
Classifier: Intended Audience :: Developers
Classifier: License :: OSI Approved :: Apache Software License
Classifier: Programming Language :: Python :: 3
Classifier: Programming Language :: Python :: 3.9
Classifier: Programming Language :: Python :: 3.10
Classifier: Programming Language :: Python :: 3.11
Classifier: Topic :: Software Development :: Libraries :: Python Modules
Classifier: Topic :: Software Development :: Quality Assurance
Requires-Python: >=3.9
Requires-Dist: click>=8.0.0
Requires-Dist: rich>=10.0.0
Provides-Extra: dev
Requires-Dist: pytest-cov>=3.0.0; extra == 'dev'
Requires-Dist: pytest>=7.0.0; extra == 'dev'
Requires-Dist: ruff>=0.1.0; extra == 'dev'
